seamm_ff_util/__init__.py
seamm_ff_util/_version.py
seamm_ff_util/dreiding.py
seamm_ff_util/eex.py
seamm_ff_util/ff_assigner.py
seamm_ff_util/forcefield.py
seamm_ff_util/metadata.py
seamm_ff_util/reaxff.py
seamm_ff_util/tabulate_function.py
seamm_ff_util-2025.8.1.dist-info/licenses/AUTHORS.rst
seamm_ff_util-2025.8.1.dist-info/licenses/LICENSE
seamm_ff_util-2025.8.1.dist-info/METADATA
seamm_ff_util-2025.8.1.dist-info/WHEEL
seamm_ff_util-2025.8.1.dist-info/entry_points.txt
seamm_ff_util-2025.8.1.dist-info/top_level.txt
seamm_ff_util-2025.8.1.dist-info/RECORD
